kroky/__init__.py
kroky/main.py
kroky-0.4.0.dist-info/METADATA
kroky-0.4.0.dist-info/WHEEL
kroky-0.4.0.dist-info/top_level.txt
kroky-0.4.0.dist-info/RECORD
