Metadata-Version: 2.1
Name: kroky
Version: 0.4.0
Summary: A Python wrapper for interacting with the Kroky meal service website.
Home-page: https://github.com/Jonontop/kroky-library
Author: Jon Pečar Anželak
Author-email: your.email@example.com
Classifier: Programming Language :: Python :: 3
Classifier: License :: OSI Approved :: MIT License
Classifier: Operating System :: OS Independent
Requires-Python: >=3.6
Requires-Dist: requests
Requires-Dist: beautifulsoup4
